{
	"yolky1" : 
	{
		"stats" :
		{
			"attack" : 1,
			"maxhp" : 10,
			"speed" : 5
		},
		"model" : "Yolky1Model",
		"actions" : 
		[
			"test_magic",
			"test_ranged",
			"test",
			"test_ranged"
		]
	},
	"yolky2" : 
	{
		"stats" :
		{
			"attack" : 1,
			"maxhp" : 10,
			"speed" : 5
		},
		"model" : "Yolky2Model",
		"actions" : 
		[
			"test_magic",
			"test_ranged",
			"test_ranged",
			"test"
		]
	},
	"yolky3" : 
	{
		"stats" :
		{
			"attack" : 1,
			"maxhp" : 10,
			"speed" : 5
		},
		"model" : "Yolky3Model",
		"actions" : 
		[
			"test_magic",
			"test",
			"test_ranged",
			"test"
		]
	},
	"shruumo" : 
	{
		"stats" :
		{
			"attack" : 1,
			"maxhp" : 10,
			"speed" : 6
		},
		"model" : "ShruumoModel",
		"actions" : 
		[
			"front_attack",
			"front_attack",
			"front_attack",
			"front_attack"
		]
	},
	"wisperina" : 
	{
		"stats" :
		{
			"attack" : 1,
			"maxhp" : 10,
			"speed" : 6
		},
		"model" : "WisperinaModel",
		"actions" : 
		[
			"front_attack",
			"front_attack",
			"front_attack",
			"front_attack"
		]
	},
	"bomborolo" : 
	{
		"stats" :
		{
			"attack" : 1,
			"maxhp" : 10,
			"speed" : 7
		},
		"model" : "BomboroloModel",
		"actions" : 
		[
			"test_magic",
			"test_magic",
			"test_magic",
			"test_magic"
		]
	},
}